ccda_to_fhir/__init__.py
ccda_to_fhir/constants.py
ccda_to_fhir/convert.py
ccda_to_fhir/exceptions.py
ccda_to_fhir/id_generator.py
ccda_to_fhir/logging_config.py
ccda_to_fhir/profiling.py
ccda_to_fhir/template_registry.py
ccda_to_fhir/types.py
ccda_to_fhir/validation.py
ccda_to_fhir/ccda/__init__.py
ccda_to_fhir/ccda/parser.py
ccda_to_fhir/ccda/models/__init__.py
ccda_to_fhir/ccda/models/act.py
ccda_to_fhir/ccda/models/author.py
ccda_to_fhir/ccda/models/clinical_document.py
ccda_to_fhir/ccda/models/datatypes.py
ccda_to_fhir/ccda/models/encounter.py
ccda_to_fhir/ccda/models/observation.py
ccda_to_fhir/ccda/models/organizer.py
ccda_to_fhir/ccda/models/participant.py
ccda_to_fhir/ccda/models/performer.py
ccda_to_fhir/ccda/models/procedure.py
ccda_to_fhir/ccda/models/record_target.py
ccda_to_fhir/ccda/models/section.py
ccda_to_fhir/ccda/models/struc_doc.py
ccda_to_fhir/ccda/models/substance_administration.py
ccda_to_fhir/ccda/models/supply.py
ccda_to_fhir/converters/__init__.py
ccda_to_fhir/converters/allergy_intolerance.py
ccda_to_fhir/converters/author_extractor.py
ccda_to_fhir/converters/base.py
ccda_to_fhir/converters/bundle.py
ccda_to_fhir/converters/careplan.py
ccda_to_fhir/converters/careteam.py
ccda_to_fhir/converters/code_systems.py
ccda_to_fhir/converters/composition.py
ccda_to_fhir/converters/condition.py
ccda_to_fhir/converters/device.py
ccda_to_fhir/converters/diagnostic_report.py
ccda_to_fhir/converters/document_reference.py
ccda_to_fhir/converters/encounter.py
ccda_to_fhir/converters/goal.py
ccda_to_fhir/converters/immunization.py
ccda_to_fhir/converters/informant_extractor.py
ccda_to_fhir/converters/location.py
ccda_to_fhir/converters/medication.py
ccda_to_fhir/converters/medication_dispense.py
ccda_to_fhir/converters/medication_request.py
ccda_to_fhir/converters/medication_statement.py
ccda_to_fhir/converters/note_activity.py
ccda_to_fhir/converters/observation.py
ccda_to_fhir/converters/organization.py
ccda_to_fhir/converters/patient.py
ccda_to_fhir-0.1.1.dist-info/METADATA
ccda_to_fhir-0.1.1.dist-info/WHEEL
ccda_to_fhir-0.1.1.dist-info/licenses/LICENSE
ccda_to_fhir-0.1.1.dist-info/RECORD
