Metadata-Version: 2.4
Name: ccda-to-fhir
Version: 0.1.1
Summary: A Python library to convert C-CDA documents to FHIR R4B resources
Project-URL: Homepage, https://github.com/nurra/ccda-to-fhir
Project-URL: Documentation, https://github.com/nurra/ccda-to-fhir#readme
Project-URL: Repository, https://github.com/nurra/ccda-to-fhir.git
Project-URL: Issues, https://github.com/nurra/ccda-to-fhir/issues
Author-email: Nurra <hello@nurra.ai>
License: MIT
License-File: LICENSE
Keywords: ccda,cda,fhir,healthcare,hl7,interoperability,r4b
Classifier: Development Status :: 3 - Alpha
Classifier: Intended Audience :: Developers
Classifier: Intended Audience :: Healthcare Industry
Classifier: License :: OSI Approved :: MIT License
Classifier: Operating System :: OS Independent
Classifier: Programming Language :: Python :: 3
Classifier: Programming Language :: Python :: 3.10
Classifier: Programming Language :: Python :: 3.11
Classifier: Programming Language :: Python :: 3.12
Classifier: Programming Language :: Python :: 3.13
Classifier: Topic :: Scientific/Engineering :: Medical Science Apps.
Classifier: Typing :: Typed
Requires-Python: >=3.10
Requires-Dist: fhir-resources>=8.1.0
Requires-Dist: lxml>=5.0
Requires-Dist: pydantic>=2.0
Provides-Extra: dev
Requires-Dist: lxml-stubs>=0.5; extra == 'dev'
Requires-Dist: mypy>=1.0; extra == 'dev'
Requires-Dist: pytest-cov>=4.0; extra == 'dev'
Requires-Dist: pytest>=8.0; extra == 'dev'
Requires-Dist: ruff>=0.8; extra == 'dev'
